hetman_kit_localize/__init__.py
hetman_kit_localize/localize.py
hetman_kit_localize-1.0.1.dist-info/licenses/LICENSE
hetman_kit_localize-1.0.1.dist-info/METADATA
hetman_kit_localize-1.0.1.dist-info/WHEEL
hetman_kit_localize-1.0.1.dist-info/top_level.txt
hetman_kit_localize-1.0.1.dist-info/RECORD
