Metadata-Version: 2.4
Name: hetman-kit-localize
Version: 1.0.1
Summary: Hetman Kit Localize provides thread-safe locale management using context variables. It enables concurrent execution with different locale settings per context.
Author-email: Hetman <degadupeko@my-relay.app>
Project-URL: Homepage, https://github.com/hetman-app/hetman-codetable
Project-URL: Documentation, https://github.com/hetman-app/hetman-codetable
Project-URL: Repository, https://github.com/hetman-app/hetman-codetable
Project-URL: Issues, https://github.com/hetman-app/hetman-codetable/issues
Classifier: Programming Language :: Python :: 3.12
Classifier: Programming Language :: Python :: 3.13
Classifier: Programming Language :: Python :: 3.14
Requires-Python: >=3.12
License-File: LICENSE
Dynamic: license-file
